{
  "type": "FeatureCollection",
  "features": [
    {
      "type": "Feature",
      "properties": {
        "alpha3": "srb",
        "generator": "tool/simplify_polygons.dart (bbox simplification)"
      },
      "geometry": {
        "type": "Polygon",
        "coordinates": [
          [
            [
              18.81702,
              41.855827
            ],
            [
              23.004997,
              41.855827
            ],
            [
              23.004997,
              46.181389
            ],
            [
              18.81702,
              46.181389
            ],
            [
              18.81702,
              41.855827
            ]
          ]
        ]
      }
    }
  ]
}